[
  {
    "team_a": "NXT",
    "team_b": "NXT",
    "event_name": "WWE NXT",
    "poster_id": "NXT-NXT-10092025.png",
    "match_type": "team_vs_team"
  },
  {
    "team_a": "UFC 324 | Prelims",
    "team_b": "",
    "event_name": "UFC 324",
    "poster_id": "UFC-324-Prelims-24012026.png",
    "match_type": "single_event"
  },
  {
    "team_a": "WWE Royal Rumble",
    "team_b": "",
    "event_name": "WWE Royal Rumble",
    "poster_id": "WWE-Royal-Rumble-31012026.png",
    "match_type": "single_event"
  },
  {
    "team_a": "Supercross Rd. 4: Houston",
    "team_b": "",
    "event_name": "Supercross Rd. 4: Houston",
    "poster_id": "Supercross-Rd.-4-Houston-01022026.png",
    "match_type": "single_event"
  },
  {
    "team_a": "England",
    "team_b": "Pakistan",
    "event_name": "ICC T20 World Cup",
    "poster_id": "England-Pakistan-24022026.png",
    "match_type": "team_vs_team"
  },
  {
    "team_a": "South Africa Women",
    "team_b": "Pakistan Women",
    "event_name": "ICC Women's Championship",
    "poster_id": "South-Africa-Women-Pakistan-Women-25022026.png",
    "match_type": "team_vs_team"
  },
  {
    "team_a": "Bayer 04 Leverkusen",
    "team_b": "Olympiacos FC",
    "event_name": "UEFA Champions League",
    "poster_id": "Bayer-04-Leverkusen-Olympiacos-FC-24022026.png",
    "match_type": "team_vs_team"
  },
  {
    "team_a": "Inter",
    "team_b": "Bodø/Glimt",
    "event_name": "UEFA Champions League",
    "poster_id": "Inter-BodøGlimt-24022026.png",
    "match_type": "team_vs_team"
  },
  {
    "team_a": "Newcastle United",
    "team_b": "Qarabağ FK",
    "event_name": "UEFA Champions League",
    "poster_id": "Newcastle-United-Qarabağ-FK-24022026.png",
    "match_type": "team_vs_team"
  }
]